pyAudioAnalysis/__init__.py
pyAudioAnalysis/analyzeMovieSound.py
pyAudioAnalysis/audacityAnnotation2WAVs.py
pyAudioAnalysis/audioAnalysis.py
pyAudioAnalysis/audioAnalysisRecordAlsa.py
pyAudioAnalysis/audioBasicIO.py
pyAudioAnalysis/audioFeatureExtraction.py
pyAudioAnalysis/audioSegmentation.py
pyAudioAnalysis/audioTrainTest.py
pyAudioAnalysis/audioVisualization.py
pyAudioAnalysis/convertToWav.py
pyAudioAnalysis/utilities.py
pyAudioAnalysis-0.2.4.dist-info/METADATA
pyAudioAnalysis-0.2.4.dist-info/RECORD
pyAudioAnalysis-0.2.4.dist-info/WHEEL
pyAudioAnalysis-0.2.4.dist-info/top_level.txt
